{"type":"FeatureCollection","features":[{"id":"ef2a7b2ef5a8d0a3c0e217846fc3cf97","type":"Feature","properties":{"name":"我的标记","type":"symbol","color":"#FFF000","size":30},"geometry":{"coordinates":[100.24048866403075,25.605647418664347],"type":"Point"}}]}